{"version":3,"kind":"Article","sha256":"cfaaa4fdb16b6b729ac87df943548d9672daa9e67abbc6796513d1001180d173","slug":"gallery","location":"/gallery.md","dependencies":[],"frontmatter":{"title":"Gallery","content_includes_title":false,"authors":[{"id":"Rosie Shewell Brockway","name":"Rosie Shewell Brockway"}],"numbering":{"code":{"enabled":false},"equation":{"enabled":false},"heading_1":{"enabled":true},"heading_2":{"enabled":true},"heading_3":{"enabled":true},"heading_4":{"enabled":true},"heading_5":{"enabled":true},"heading_6":{"enabled":true}},"thumbnail":"/7-colour-3a-50f7b843ef20e63ebea624b4801e4051.jpg","exports":[{"format":"md","filename":"gallery.md","url":"/gallery-9055858a05169e8f866cd7922bc8cdaa.md"}]},"mdast":{"type":"root","children":[{"type":"block","children":[{"type":"heading","depth":2,"position":{"start":{"line":3,"column":1},"end":{"line":3,"column":1}},"children":[{"type":"text","value":"Torus","position":{"start":{"line":3,"column":1},"end":{"line":3,"column":1}},"key":"BaSstd1ZEr"}],"identifier":"torus","label":"Torus","html_id":"torus","implicit":true,"enumerator":"1","key":"fs7pxxzl3W"},{"type":"heading","depth":3,"position":{"start":{"line":5,"column":1},"end":{"line":5,"column":1}},"children":[{"type":"text","value":"March 2026","position":{"start":{"line":5,"column":1},"end":{"line":5,"column":1}},"key":"Urml8V13DY"}],"identifier":"march-2026","label":"March 2026","html_id":"march-2026","implicit":true,"enumerator":"1.1","key":"SlGK6evJmA"},{"type":"container","kind":"figure","children":[{"type":"container","kind":"figure","subcontainer":true,"children":[{"type":"image","url":"/7-colour-3a-50f7b843ef20e63ebea624b4801e4051.jpg","alt":"Made using this pattern.","position":{"start":{"line":11,"column":1},"end":{"line":11,"column":1}},"data":{"altTextIsAutoGenerated":true},"key":"JtCDfKYwhw","urlSource":"figs/7-colour-3a.jpg"},{"type":"caption","children":[{"type":"paragraph","children":[{"type":"captionNumber","kind":"figure","label":"fig:7-colour-3-a","identifier":"fig:7-colour-3-a","html_id":"fig-7-colour-3-a","enumerator":"1a","children":[{"type":"text","value":"(","key":"dvXlIeUjT2"},{"type":"text","value":"a","key":"ue7zeMJ5s3"},{"type":"text","value":")","key":"exIm39dETs"}],"template":"({subEnumerator})","key":"CbaGX2tgk9"}],"key":"H3PtC9HpJK"}],"key":"x9PxSZPMWG"}],"parentEnumerator":"1","enumerator":"a","html_id":"fig-7-colour-3-a","label":"fig:7-colour-3-a","identifier":"fig:7-colour-3-a","implicit":true,"key":"vN6fuipSBP"},{"type":"container","kind":"figure","subcontainer":true,"children":[{"type":"image","url":"/7-colour-3b-34db794518d9f3598bd9119e461e9a60.jpg","alt":"Made using this pattern.","position":{"start":{"line":13,"column":1},"end":{"line":13,"column":1}},"data":{"altTextIsAutoGenerated":true},"key":"dWPOSoPpmS","urlSource":"figs/7-colour-3b.jpg"},{"type":"caption","children":[{"type":"paragraph","children":[{"type":"captionNumber","kind":"figure","label":"fig:7-colour-3-b","identifier":"fig:7-colour-3-b","html_id":"fig-7-colour-3-b","enumerator":"1b","children":[{"type":"text","value":"(","key":"wpGTcYNNBi"},{"type":"text","value":"b","key":"H52OqD4r2B"},{"type":"text","value":")","key":"LyT5ff6UUq"}],"template":"({subEnumerator})","key":"BtmZcEkkcM"}],"key":"bfHOtqD4NN"}],"key":"gGUPlXYUC3"}],"parentEnumerator":"1","enumerator":"b","html_id":"fig-7-colour-3-b","label":"fig:7-colour-3-b","identifier":"fig:7-colour-3-b","implicit":true,"key":"DvpesQDgla"},{"type":"caption","children":[{"type":"paragraph","position":{"start":{"line":15,"column":1},"end":{"line":15,"column":1}},"children":[{"type":"captionNumber","kind":"figure","label":"fig:7-colour-3","identifier":"fig:7-colour-3","html_id":"fig-7-colour-3","enumerator":"1","children":[{"type":"text","value":"Figure ","key":"snLMSAkpqC"},{"type":"text","value":"1","key":"v5FQEvD03M"},{"type":"text","value":":","key":"eXkEI5MD9Q"}],"template":"Figure %s:","key":"hgG55vY8a0"},{"type":"text","value":"Made using ","position":{"start":{"line":15,"column":1},"end":{"line":15,"column":1}},"key":"WzPGfgOZbq"},{"type":"crossReference","position":{"start":{"line":15,"column":1},"end":{"line":15,"column":1}},"children":[{"type":"text","value":"this pattern","position":{"start":{"line":15,"column":1},"end":{"line":15,"column":1}},"key":"S5QPMJLvVB"}],"identifier":"7-col","label":"7-col","kind":"heading","template":"Section %s","enumerator":"1","resolved":true,"html_id":"id-7-col","remote":true,"url":"/colour-work-patterns","dataUrl":"/colour-work-patterns.json","key":"GqWAFnvDym"},{"type":"text","value":".","position":{"start":{"line":15,"column":1},"end":{"line":15,"column":1}},"key":"vRGiKYhjNe"}],"key":"mtheinaN5K"}],"key":"tIsKJ1v7gv"}],"class":"grid grid-cols-2 items-end gap-4","label":"fig:7-colour-3","identifier":"fig:7-colour-3","enumerator":"1","html_id":"fig-7-colour-3","key":"mwuYHBpWig"},{"type":"paragraph","position":{"start":{"line":18,"column":1},"end":{"line":18,"column":1}},"children":[{"type":"text","value":"This was Attempt 3 at making this pattern work, and uses parameters ","position":{"start":{"line":18,"column":1},"end":{"line":18,"column":1}},"key":"u5D1uN72Uh"},{"type":"inlineMath","value":"R = 4.8","position":{"start":{"line":18,"column":1},"end":{"line":18,"column":1}},"html":"<span class=\"katex\"><span class=\"katex-mathml\"><math xmlns=\"http://www.w3.org/1998/Math/MathML\"><semantics><mrow><mi>R</mi><mo>=</mo><mn>4.8</mn></mrow><annotation encoding=\"application/x-tex\">R = 4.8</annotation></semantics></math></span><span class=\"katex-html\" aria-hidden=\"true\"><span class=\"base\"><span class=\"strut\" style=\"height:0.6833em;\"></span><span class=\"mord mathnormal\" style=\"margin-right:0.00773em;\">R</span><span class=\"mspace\" style=\"margin-right:0.2778em;\"></span><span class=\"mrel\">=</span><span class=\"mspace\" style=\"margin-right:0.2778em;\"></span></span><span class=\"base\"><span class=\"strut\" style=\"height:0.6444em;\"></span><span class=\"mord\">4.8</span></span></span></span>","key":"OSLV0wDnlf"},{"type":"text","value":", ","position":{"start":{"line":18,"column":1},"end":{"line":18,"column":1}},"key":"XV7zYucCKu"},{"type":"inlineMath","value":"r = 1.6","position":{"start":{"line":18,"column":1},"end":{"line":18,"column":1}},"html":"<span class=\"katex\"><span class=\"katex-mathml\"><math xmlns=\"http://www.w3.org/1998/Math/MathML\"><semantics><mrow><mi>r</mi><mo>=</mo><mn>1.6</mn></mrow><annotation encoding=\"application/x-tex\">r = 1.6</annotation></semantics></math></span><span class=\"katex-html\" aria-hidden=\"true\"><span class=\"base\"><span class=\"strut\" style=\"height:0.4306em;\"></span><span class=\"mord mathnormal\" style=\"margin-right:0.02778em;\">r</span><span class=\"mspace\" style=\"margin-right:0.2778em;\"></span><span class=\"mrel\">=</span><span class=\"mspace\" style=\"margin-right:0.2778em;\"></span></span><span class=\"base\"><span class=\"strut\" style=\"height:0.6444em;\"></span><span class=\"mord\">1.6</span></span></span></span>","key":"LRF4EtAwdR"},{"type":"text","value":", ","position":{"start":{"line":18,"column":1},"end":{"line":18,"column":1}},"key":"P5DPSHdZRT"},{"type":"inlineMath","value":"w = 0.48","position":{"start":{"line":18,"column":1},"end":{"line":18,"column":1}},"html":"<span class=\"katex\"><span class=\"katex-mathml\"><math xmlns=\"http://www.w3.org/1998/Math/MathML\"><semantics><mrow><mi>w</mi><mo>=</mo><mn>0.48</mn></mrow><annotation encoding=\"application/x-tex\">w = 0.48</annotation></semantics></math></span><span class=\"katex-html\" aria-hidden=\"true\"><span class=\"base\"><span class=\"strut\" style=\"height:0.4306em;\"></span><span class=\"mord mathnormal\" style=\"margin-right:0.02691em;\">w</span><span class=\"mspace\" style=\"margin-right:0.2778em;\"></span><span class=\"mrel\">=</span><span class=\"mspace\" style=\"margin-right:0.2778em;\"></span></span><span class=\"base\"><span class=\"strut\" style=\"height:0.6444em;\"></span><span class=\"mord\">0.48</span></span></span></span>","key":"iaO8Qa4FXK"},{"type":"text","value":" and ","position":{"start":{"line":18,"column":1},"end":{"line":18,"column":1}},"key":"CTjxwLW62D"},{"type":"inlineMath","value":"h = 0.863","position":{"start":{"line":18,"column":1},"end":{"line":18,"column":1}},"html":"<span class=\"katex\"><span class=\"katex-mathml\"><math xmlns=\"http://www.w3.org/1998/Math/MathML\"><semantics><mrow><mi>h</mi><mo>=</mo><mn>0.863</mn></mrow><annotation encoding=\"application/x-tex\">h = 0.863</annotation></semantics></math></span><span class=\"katex-html\" aria-hidden=\"true\"><span class=\"base\"><span class=\"strut\" style=\"height:0.6944em;\"></span><span class=\"mord mathnormal\">h</span><span class=\"mspace\" style=\"margin-right:0.2778em;\"></span><span class=\"mrel\">=</span><span class=\"mspace\" style=\"margin-right:0.2778em;\"></span></span><span class=\"base\"><span class=\"strut\" style=\"height:0.6444em;\"></span><span class=\"mord\">0.863</span></span></span></span>","key":"O5WjLD8E15"},{"type":"text","value":". See ","position":{"start":{"line":18,"column":1},"end":{"line":18,"column":1}},"key":"NEApPpC6Le"},{"type":"crossReference","position":{"start":{"line":18,"column":1},"end":{"line":18,"column":1}},"children":[{"type":"text","value":"Figure ","key":"SsKFw2NfYo"},{"type":"text","value":"5","key":"i11fGQWxTQ"}],"identifier":"fig:7-colour-2","label":"fig:7-colour-2","kind":"figure","template":"Figure %s","enumerator":"5","resolved":true,"html_id":"fig-7-colour-2","key":"JdDkQPuQzm"},{"type":"text","value":" for Attempts 1 and 2. The only problem with Attempt 2 was its size (6cm diameter). Attempt 3 is twice this. Attempt 1 assumed square stitches, which was a mistake, as the colour work method involved keeping unused yarns inside each stitch, making the dcs taller.","position":{"start":{"line":18,"column":1},"end":{"line":18,"column":1}},"key":"cEys2SWCJW"}],"key":"JLvEyqVjkU"},{"type":"heading","depth":3,"position":{"start":{"line":20,"column":1},"end":{"line":20,"column":1}},"children":[{"type":"text","value":"Feb 2026","position":{"start":{"line":20,"column":1},"end":{"line":20,"column":1}},"key":"ov5Am3i1EB"}],"identifier":"feb-2026","label":"Feb 2026","html_id":"feb-2026","implicit":true,"enumerator":"1.2","key":"fdzfWFcP9Y"},{"type":"container","kind":"figure","children":[{"type":"image","url":"/Feb26_torus_2-fc7a0424b43d168f3cd3c56d1228ebe4.jpg","alt":"R=4, r=1.78, w=0.4, h=0.4, N=14.","width":"400","data":{"altTextIsAutoGenerated":true},"key":"p1HonWjgvn","urlSource":"figs/Feb26_torus_2.jpg"},{"type":"caption","children":[{"type":"paragraph","position":{"start":{"line":24,"column":1},"end":{"line":24,"column":1}},"children":[{"type":"captionNumber","kind":"figure","label":"fig:Feb26_torus_2","identifier":"fig:feb26_torus_2","html_id":"fig-feb26-torus-2","enumerator":"2","children":[{"type":"text","value":"Figure ","key":"cze7Mlxf7D"},{"type":"text","value":"2","key":"ML6ZgrhS4W"},{"type":"text","value":":","key":"maQ26AcHkx"}],"template":"Figure %s:","key":"mwLzexU289"},{"type":"inlineMath","value":"R=4","position":{"start":{"line":24,"column":1},"end":{"line":24,"column":1}},"html":"<span class=\"katex\"><span class=\"katex-mathml\"><math xmlns=\"http://www.w3.org/1998/Math/MathML\"><semantics><mrow><mi>R</mi><mo>=</mo><mn>4</mn></mrow><annotation encoding=\"application/x-tex\">R=4</annotation></semantics></math></span><span class=\"katex-html\" aria-hidden=\"true\"><span class=\"base\"><span class=\"strut\" style=\"height:0.6833em;\"></span><span class=\"mord mathnormal\" style=\"margin-right:0.00773em;\">R</span><span class=\"mspace\" style=\"margin-right:0.2778em;\"></span><span class=\"mrel\">=</span><span class=\"mspace\" style=\"margin-right:0.2778em;\"></span></span><span class=\"base\"><span class=\"strut\" style=\"height:0.6444em;\"></span><span class=\"mord\">4</span></span></span></span>","key":"GfUysF6Fn0"},{"type":"text","value":", ","position":{"start":{"line":24,"column":1},"end":{"line":24,"column":1}},"key":"iUtLKYeMG3"},{"type":"inlineMath","value":"r=1.78","position":{"start":{"line":24,"column":1},"end":{"line":24,"column":1}},"html":"<span class=\"katex\"><span class=\"katex-mathml\"><math xmlns=\"http://www.w3.org/1998/Math/MathML\"><semantics><mrow><mi>r</mi><mo>=</mo><mn>1.78</mn></mrow><annotation encoding=\"application/x-tex\">r=1.78</annotation></semantics></math></span><span class=\"katex-html\" aria-hidden=\"true\"><span class=\"base\"><span class=\"strut\" style=\"height:0.4306em;\"></span><span class=\"mord mathnormal\" style=\"margin-right:0.02778em;\">r</span><span class=\"mspace\" style=\"margin-right:0.2778em;\"></span><span class=\"mrel\">=</span><span class=\"mspace\" style=\"margin-right:0.2778em;\"></span></span><span class=\"base\"><span class=\"strut\" style=\"height:0.6444em;\"></span><span class=\"mord\">1.78</span></span></span></span>","key":"lh4VAC5jHi"},{"type":"text","value":", ","position":{"start":{"line":24,"column":1},"end":{"line":24,"column":1}},"key":"pVmMtefPBa"},{"type":"inlineMath","value":"w=0.4","position":{"start":{"line":24,"column":1},"end":{"line":24,"column":1}},"html":"<span class=\"katex\"><span class=\"katex-mathml\"><math xmlns=\"http://www.w3.org/1998/Math/MathML\"><semantics><mrow><mi>w</mi><mo>=</mo><mn>0.4</mn></mrow><annotation encoding=\"application/x-tex\">w=0.4</annotation></semantics></math></span><span class=\"katex-html\" aria-hidden=\"true\"><span class=\"base\"><span class=\"strut\" style=\"height:0.4306em;\"></span><span class=\"mord mathnormal\" style=\"margin-right:0.02691em;\">w</span><span class=\"mspace\" style=\"margin-right:0.2778em;\"></span><span class=\"mrel\">=</span><span class=\"mspace\" style=\"margin-right:0.2778em;\"></span></span><span class=\"base\"><span class=\"strut\" style=\"height:0.6444em;\"></span><span class=\"mord\">0.4</span></span></span></span>","key":"vIrgHVcgFv"},{"type":"text","value":", ","position":{"start":{"line":24,"column":1},"end":{"line":24,"column":1}},"key":"q1BnTilncL"},{"type":"inlineMath","value":"h=0.4","position":{"start":{"line":24,"column":1},"end":{"line":24,"column":1}},"html":"<span class=\"katex\"><span class=\"katex-mathml\"><math xmlns=\"http://www.w3.org/1998/Math/MathML\"><semantics><mrow><mi>h</mi><mo>=</mo><mn>0.4</mn></mrow><annotation encoding=\"application/x-tex\">h=0.4</annotation></semantics></math></span><span class=\"katex-html\" aria-hidden=\"true\"><span class=\"base\"><span class=\"strut\" style=\"height:0.6944em;\"></span><span class=\"mord mathnormal\">h</span><span class=\"mspace\" style=\"margin-right:0.2778em;\"></span><span class=\"mrel\">=</span><span class=\"mspace\" style=\"margin-right:0.2778em;\"></span></span><span class=\"base\"><span class=\"strut\" style=\"height:0.6444em;\"></span><span class=\"mord\">0.4</span></span></span></span>","key":"bxZkB5GYkT"},{"type":"text","value":", ","position":{"start":{"line":24,"column":1},"end":{"line":24,"column":1}},"key":"Be2oPXr1ok"},{"type":"inlineMath","value":"N=14","position":{"start":{"line":24,"column":1},"end":{"line":24,"column":1}},"html":"<span class=\"katex\"><span class=\"katex-mathml\"><math xmlns=\"http://www.w3.org/1998/Math/MathML\"><semantics><mrow><mi>N</mi><mo>=</mo><mn>14</mn></mrow><annotation encoding=\"application/x-tex\">N=14</annotation></semantics></math></span><span class=\"katex-html\" aria-hidden=\"true\"><span class=\"base\"><span class=\"strut\" style=\"height:0.6833em;\"></span><span class=\"mord mathnormal\" style=\"margin-right:0.10903em;\">N</span><span class=\"mspace\" style=\"margin-right:0.2778em;\"></span><span class=\"mrel\">=</span><span class=\"mspace\" style=\"margin-right:0.2778em;\"></span></span><span class=\"base\"><span class=\"strut\" style=\"height:0.6444em;\"></span><span class=\"mord\">14</span></span></span></span>","key":"HT0dBSmc0T"},{"type":"text","value":".","position":{"start":{"line":24,"column":1},"end":{"line":24,"column":1}},"key":"HM9r0NILmB"}],"key":"lD7CU5RaET"}],"key":"Q7KgX6iNaj"}],"label":"fig:Feb26_torus_2","identifier":"fig:feb26_torus_2","enumerator":"2","html_id":"fig-feb26-torus-2","key":"s0jR8PWcsy"},{"type":"paragraph","position":{"start":{"line":27,"column":1},"end":{"line":27,"column":1}},"children":[{"type":"text","value":"This is the closest in accuracy yet. Worked using hdc (UK) and colour work where the the non-active thread runs inside each stitch, resulting in for more uniform tension (contrast with ","position":{"start":{"line":27,"column":1},"end":{"line":27,"column":1}},"key":"XRRLIHk8Eh"},{"type":"crossReference","position":{"start":{"line":27,"column":1},"end":{"line":27,"column":1}},"children":[{"type":"text","value":"Figure ","key":"pnimdR2r37"},{"type":"text","value":"3","key":"Hj7GMbfjTr"}],"identifier":"fig:sept25_torus_2","label":"fig:Sept25_torus_2","kind":"figure","template":"Figure %s","enumerator":"3","resolved":true,"html_id":"fig-sept25-torus-2","key":"dDiO6xhpHD"},{"type":"text","value":").","position":{"start":{"line":27,"column":1},"end":{"line":27,"column":1}},"key":"xXaOTgqUL9"}],"key":"jJJSrtYi4X"},{"type":"heading","depth":3,"position":{"start":{"line":29,"column":1},"end":{"line":29,"column":1}},"children":[{"type":"text","value":"Sept 2025","position":{"start":{"line":29,"column":1},"end":{"line":29,"column":1}},"key":"dM9oqJNxh1"}],"identifier":"sept-2025","label":"Sept 2025","html_id":"sept-2025","implicit":true,"enumerator":"1.3","key":"zJW94yyyHM"},{"type":"container","kind":"figure","children":[{"type":"image","url":"/Sept25_torus_2-02f33fae44117484b6fcf9c9d2b07bed.jpg","alt":"R=5, r=2, w=0.6, h=0.63, N=10.","width":"400","data":{"altTextIsAutoGenerated":true},"key":"mOGAOPVKPN","urlSource":"figs/Sept25_torus_2.jpg"},{"type":"caption","children":[{"type":"paragraph","position":{"start":{"line":35,"column":1},"end":{"line":35,"column":1}},"children":[{"type":"captionNumber","kind":"figure","label":"fig:Sept25_torus_2","identifier":"fig:sept25_torus_2","html_id":"fig-sept25-torus-2","enumerator":"3","children":[{"type":"text","value":"Figure ","key":"vlVm8d71La"},{"type":"text","value":"3","key":"vqA8rwZOqa"},{"type":"text","value":":","key":"hVci3dCAsq"}],"template":"Figure %s:","key":"MzFGnRTGPZ"},{"type":"inlineMath","value":"R=5","position":{"start":{"line":35,"column":1},"end":{"line":35,"column":1}},"html":"<span class=\"katex\"><span class=\"katex-mathml\"><math xmlns=\"http://www.w3.org/1998/Math/MathML\"><semantics><mrow><mi>R</mi><mo>=</mo><mn>5</mn></mrow><annotation encoding=\"application/x-tex\">R=5</annotation></semantics></math></span><span class=\"katex-html\" aria-hidden=\"true\"><span class=\"base\"><span class=\"strut\" style=\"height:0.6833em;\"></span><span class=\"mord mathnormal\" style=\"margin-right:0.00773em;\">R</span><span class=\"mspace\" style=\"margin-right:0.2778em;\"></span><span class=\"mrel\">=</span><span class=\"mspace\" style=\"margin-right:0.2778em;\"></span></span><span class=\"base\"><span class=\"strut\" style=\"height:0.6444em;\"></span><span class=\"mord\">5</span></span></span></span>","key":"yb62qaCnYU"},{"type":"text","value":", ","position":{"start":{"line":35,"column":1},"end":{"line":35,"column":1}},"key":"QnDby4Skik"},{"type":"inlineMath","value":"r=2","position":{"start":{"line":35,"column":1},"end":{"line":35,"column":1}},"html":"<span class=\"katex\"><span class=\"katex-mathml\"><math xmlns=\"http://www.w3.org/1998/Math/MathML\"><semantics><mrow><mi>r</mi><mo>=</mo><mn>2</mn></mrow><annotation encoding=\"application/x-tex\">r=2</annotation></semantics></math></span><span class=\"katex-html\" aria-hidden=\"true\"><span class=\"base\"><span class=\"strut\" style=\"height:0.4306em;\"></span><span class=\"mord mathnormal\" style=\"margin-right:0.02778em;\">r</span><span class=\"mspace\" style=\"margin-right:0.2778em;\"></span><span class=\"mrel\">=</span><span class=\"mspace\" style=\"margin-right:0.2778em;\"></span></span><span class=\"base\"><span class=\"strut\" style=\"height:0.6444em;\"></span><span class=\"mord\">2</span></span></span></span>","key":"cbxnqs0XXk"},{"type":"text","value":", ","position":{"start":{"line":35,"column":1},"end":{"line":35,"column":1}},"key":"raBJiYaZge"},{"type":"inlineMath","value":"w=0.6","position":{"start":{"line":35,"column":1},"end":{"line":35,"column":1}},"html":"<span class=\"katex\"><span class=\"katex-mathml\"><math xmlns=\"http://www.w3.org/1998/Math/MathML\"><semantics><mrow><mi>w</mi><mo>=</mo><mn>0.6</mn></mrow><annotation encoding=\"application/x-tex\">w=0.6</annotation></semantics></math></span><span class=\"katex-html\" aria-hidden=\"true\"><span class=\"base\"><span class=\"strut\" style=\"height:0.4306em;\"></span><span class=\"mord mathnormal\" style=\"margin-right:0.02691em;\">w</span><span class=\"mspace\" style=\"margin-right:0.2778em;\"></span><span class=\"mrel\">=</span><span class=\"mspace\" style=\"margin-right:0.2778em;\"></span></span><span class=\"base\"><span class=\"strut\" style=\"height:0.6444em;\"></span><span class=\"mord\">0.6</span></span></span></span>","key":"IGS8yarMyo"},{"type":"text","value":", ","position":{"start":{"line":35,"column":1},"end":{"line":35,"column":1}},"key":"PoEmlAI8Ub"},{"type":"inlineMath","value":"h=0.63","position":{"start":{"line":35,"column":1},"end":{"line":35,"column":1}},"html":"<span class=\"katex\"><span class=\"katex-mathml\"><math xmlns=\"http://www.w3.org/1998/Math/MathML\"><semantics><mrow><mi>h</mi><mo>=</mo><mn>0.63</mn></mrow><annotation encoding=\"application/x-tex\">h=0.63</annotation></semantics></math></span><span class=\"katex-html\" aria-hidden=\"true\"><span class=\"base\"><span class=\"strut\" style=\"height:0.6944em;\"></span><span class=\"mord mathnormal\">h</span><span class=\"mspace\" style=\"margin-right:0.2778em;\"></span><span class=\"mrel\">=</span><span class=\"mspace\" style=\"margin-right:0.2778em;\"></span></span><span class=\"base\"><span class=\"strut\" style=\"height:0.6444em;\"></span><span class=\"mord\">0.63</span></span></span></span>","key":"Lx7U9oUJbz"},{"type":"text","value":", ","position":{"start":{"line":35,"column":1},"end":{"line":35,"column":1}},"key":"tsYLFVO3yC"},{"type":"inlineMath","value":"N=10","position":{"start":{"line":35,"column":1},"end":{"line":35,"column":1}},"html":"<span class=\"katex\"><span class=\"katex-mathml\"><math xmlns=\"http://www.w3.org/1998/Math/MathML\"><semantics><mrow><mi>N</mi><mo>=</mo><mn>10</mn></mrow><annotation encoding=\"application/x-tex\">N=10</annotation></semantics></math></span><span class=\"katex-html\" aria-hidden=\"true\"><span class=\"base\"><span class=\"strut\" style=\"height:0.6833em;\"></span><span class=\"mord mathnormal\" style=\"margin-right:0.10903em;\">N</span><span class=\"mspace\" style=\"margin-right:0.2778em;\"></span><span class=\"mrel\">=</span><span class=\"mspace\" style=\"margin-right:0.2778em;\"></span></span><span class=\"base\"><span class=\"strut\" style=\"height:0.6444em;\"></span><span class=\"mord\">10</span></span></span></span>","key":"zZsHgrpin6"},{"type":"text","value":".","position":{"start":{"line":35,"column":1},"end":{"line":35,"column":1}},"key":"xchGKaT4fr"}],"key":"id91zjGkBz"}],"key":"rsTFzx0C85"}],"label":"fig:Sept25_torus_2","identifier":"fig:sept25_torus_2","enumerator":"3","html_id":"fig-sept25-torus-2","key":"fnN2Ik6UGg"},{"type":"paragraph","position":{"start":{"line":38,"column":1},"end":{"line":38,"column":1}},"children":[{"type":"text","value":"I’m pleased with the ","position":{"start":{"line":38,"column":1},"end":{"line":38,"column":1}},"key":"Ywaxq456jj"},{"type":"link","url":"https://en.wikipedia.org/wiki/Heawood_conjecture","position":{"start":{"line":38,"column":1},"end":{"line":38,"column":1}},"children":[{"type":"text","value":"7-colouring","position":{"start":{"line":38,"column":1},"end":{"line":38,"column":1}},"key":"XxPGcVh7yI"}],"urlSource":"https://en.wikipedia.org/wiki/Heawood_conjecture","data":{"page":"Heawood_conjecture","wiki":"https://en.wikipedia.org/","lang":"en"},"internal":false,"protocol":"wiki","key":"JMKwIvto8Q"},{"type":"text","value":" as a concept, but ideally the tension would be more uniform. I think working in back loops only made this worse, especially at points where the colour changes. I plan to reattempt this soon with the colour work method of ","position":{"start":{"line":38,"column":1},"end":{"line":38,"column":1}},"key":"bcVFHwopfV"},{"type":"crossReference","position":{"start":{"line":38,"column":1},"end":{"line":38,"column":1}},"children":[{"type":"text","value":"Figure ","key":"SJbBzfsjc9"},{"type":"text","value":"2","key":"pDPFSpYyJU"}],"identifier":"fig:feb26_torus_2","label":"fig:Feb26_torus_2","kind":"figure","template":"Figure %s","enumerator":"2","resolved":true,"html_id":"fig-feb26-torus-2","key":"BXi9kCnlEb"},{"type":"text","value":".","position":{"start":{"line":38,"column":1},"end":{"line":38,"column":1}},"key":"Sm8HXhWuDB"}],"key":"oYme9y4zR7"},{"type":"container","kind":"figure","children":[{"type":"image","url":"/torus-k7-f3e71ccbdbe3f1f7868b2a85c055bf77.png","alt":"Pattern used to create . (The stitch counts are incorrect.)","width":"400","data":{"altTextIsAutoGenerated":true},"key":"VH5jnsCRuQ","urlSource":"figs/torus-k7.png"},{"type":"caption","children":[{"type":"paragraph","position":{"start":{"line":44,"column":1},"end":{"line":44,"column":1}},"children":[{"type":"captionNumber","kind":"figure","label":"fig:torus-k7","identifier":"fig:torus-k7","html_id":"fig-torus-k7","enumerator":"4","children":[{"type":"text","value":"Figure ","key":"TPe1piJP7V"},{"type":"text","value":"4","key":"RsfAYj3fAU"},{"type":"text","value":":","key":"zSySOxCkI7"}],"template":"Figure %s:","key":"VSSOnvhIcO"},{"type":"text","value":"Pattern used to create ","position":{"start":{"line":44,"column":1},"end":{"line":44,"column":1}},"key":"TYNOyiLrnB"},{"type":"crossReference","position":{"start":{"line":44,"column":1},"end":{"line":44,"column":1}},"children":[{"type":"text","value":"Figure ","key":"Tm5Zi4APjl"},{"type":"text","value":"3","key":"huE6FvqpdF"}],"identifier":"fig:sept25_torus_2","label":"fig:Sept25_torus_2","kind":"figure","template":"Figure %s","enumerator":"3","resolved":true,"html_id":"fig-sept25-torus-2","key":"tfqTiMptj7"},{"type":"text","value":". (The stitch counts are incorrect.)","position":{"start":{"line":44,"column":1},"end":{"line":44,"column":1}},"key":"qJHbG1rLS7"}],"key":"JMK9kZAotK"}],"key":"Ztd8HSRSCZ"}],"label":"fig:torus-k7","identifier":"fig:torus-k7","enumerator":"4","html_id":"fig-torus-k7","key":"IjbJLAsV5J"},{"type":"heading","depth":2,"position":{"start":{"line":47,"column":1},"end":{"line":47,"column":1}},"children":[{"type":"text","value":"Miscounts and mismeasurement (for science)","position":{"start":{"line":47,"column":1},"end":{"line":47,"column":1}},"key":"gGJgvYeLiA"}],"identifier":"miscounts-and-mismeasurement-for-science","label":"Miscounts and mismeasurement (for science)","html_id":"miscounts-and-mismeasurement-for-science","implicit":true,"enumerator":"2","key":"LuSAURqDRL"},{"type":"paragraph","position":{"start":{"line":48,"column":1},"end":{"line":48,"column":1}},"children":[{"type":"text","value":"Failure to meet the requirement ","position":{"start":{"line":48,"column":1},"end":{"line":48,"column":1}},"key":"dCoqRs1D0N"},{"type":"inlineMath","value":"h=\\frac{r\\pi}{N}","position":{"start":{"line":48,"column":1},"end":{"line":48,"column":1}},"html":"<span class=\"katex\"><span class=\"katex-mathml\"><math xmlns=\"http://www.w3.org/1998/Math/MathML\"><semantics><mrow><mi>h</mi><mo>=</mo><mfrac><mrow><mi>r</mi><mi>π</mi></mrow><mi>N</mi></mfrac></mrow><annotation encoding=\"application/x-tex\">h=\\frac{r\\pi}{N}</annotation></semantics></math></span><span class=\"katex-html\" aria-hidden=\"true\"><span class=\"base\"><span class=\"strut\" style=\"height:0.6944em;\"></span><span class=\"mord mathnormal\">h</span><span class=\"mspace\" style=\"margin-right:0.2778em;\"></span><span class=\"mrel\">=</span><span class=\"mspace\" style=\"margin-right:0.2778em;\"></span></span><span class=\"base\"><span class=\"strut\" style=\"height:1.0404em;vertical-align:-0.345em;\"></span><span class=\"mord\"><span class=\"mopen nulldelimiter\"></span><span class=\"mfrac\"><span class=\"vlist-t vlist-t2\"><span class=\"vlist-r\"><span class=\"vlist\" style=\"height:0.6954em;\"><span style=\"top:-2.655em;\"><span class=\"pstrut\" style=\"height:3em;\"></span><span class=\"sizing reset-size6 size3 mtight\"><span class=\"mord mtight\"><span class=\"mord mathnormal mtight\" style=\"margin-right:0.10903em;\">N</span></span></span></span><span style=\"top:-3.23em;\"><span class=\"pstrut\" style=\"height:3em;\"></span><span class=\"frac-line\" style=\"border-bottom-width:0.04em;\"></span></span><span style=\"top:-3.394em;\"><span class=\"pstrut\" style=\"height:3em;\"></span><span class=\"sizing reset-size6 size3 mtight\"><span class=\"mord mtight\"><span class=\"mord mathnormal mtight\" style=\"margin-right:0.02778em;\">r</span><span class=\"mord mathnormal mtight\" style=\"margin-right:0.03588em;\">π</span></span></span></span></span><span class=\"vlist-s\">​</span></span><span class=\"vlist-r\"><span class=\"vlist\" style=\"height:0.345em;\"><span></span></span></span></span></span><span class=\"mclose nulldelimiter\"></span></span></span></span></span>","key":"zkjrV8Ff52"},{"type":"text","value":" and/or mis-measurement of stitch sizes results in geometric “torusoids” (surfaces of revolution of non-circular ellipses). This appears to be most noticeable when ","position":{"start":{"line":48,"column":1},"end":{"line":48,"column":1}},"key":"t8JzNlPJN3"},{"type":"inlineMath","value":"R/r","position":{"start":{"line":48,"column":1},"end":{"line":48,"column":1}},"html":"<span class=\"katex\"><span class=\"katex-mathml\"><math xmlns=\"http://www.w3.org/1998/Math/MathML\"><semantics><mrow><mi>R</mi><mi mathvariant=\"normal\">/</mi><mi>r</mi></mrow><annotation encoding=\"application/x-tex\">R/r</annotation></semantics></math></span><span class=\"katex-html\" aria-hidden=\"true\"><span class=\"base\"><span class=\"strut\" style=\"height:1em;vertical-align:-0.25em;\"></span><span class=\"mord mathnormal\" style=\"margin-right:0.00773em;\">R</span><span class=\"mord\">/</span><span class=\"mord mathnormal\" style=\"margin-right:0.02778em;\">r</span></span></span></span>","key":"JU6fd32qFi"},{"type":"text","value":" is close to ","position":{"start":{"line":48,"column":1},"end":{"line":48,"column":1}},"key":"TyuxsMRvAT"},{"type":"text","value":"1","position":{"start":{"line":48,"column":1},"end":{"line":48,"column":1}},"key":"Cx6sfDEiPP"},{"type":"text","value":".","position":{"start":{"line":48,"column":1},"end":{"line":48,"column":1}},"key":"TVU3mm8D9m"}],"key":"mvuh3505Gt"},{"type":"heading","depth":3,"position":{"start":{"line":50,"column":1},"end":{"line":50,"column":1}},"children":[{"type":"text","value":"March 2026","position":{"start":{"line":50,"column":1},"end":{"line":50,"column":1}},"key":"yo8zfQYP2v"}],"identifier":"march-2026","label":"March 2026","html_id":"march-2026-1","implicit":true,"enumerator":"2.1","key":"iOXEaPyBSS"},{"type":"container","kind":"figure","children":[{"type":"image","url":"/7-colour-2a-a41073fb235aab11742d8e4ec4eaff28.jpg","alt":"Earlier versions of this pattern. Attempt 1 (left): R=2.4, r=0.8, w=h=0.4; Attempt 2 (right)  R = 2.4, r = 0.8, w = 0.48, h=0.863.","data":{"altTextIsAutoGenerated":true},"key":"TBphpVijJi","urlSource":"figs/7-colour-2a.jpg"},{"type":"caption","children":[{"type":"paragraph","position":{"start":{"line":55,"column":1},"end":{"line":55,"column":1}},"children":[{"type":"captionNumber","kind":"figure","label":"fig:7-colour-2","identifier":"fig:7-colour-2","html_id":"fig-7-colour-2","enumerator":"5","children":[{"type":"text","value":"Figure ","key":"rdlHweglp8"},{"type":"text","value":"5","key":"K4TNRkLyLU"},{"type":"text","value":":","key":"ohmwY1g3FG"}],"template":"Figure %s:","key":"gDLAwJhlPX"},{"type":"text","value":"Earlier versions of ","position":{"start":{"line":55,"column":1},"end":{"line":55,"column":1}},"key":"rZgauC3Eww"},{"type":"crossReference","position":{"start":{"line":55,"column":1},"end":{"line":55,"column":1}},"children":[{"type":"text","value":"this pattern","position":{"start":{"line":55,"column":1},"end":{"line":55,"column":1}},"key":"Pb5dFrkLEu"}],"identifier":"7-col","label":"7-col","kind":"heading","template":"Section %s","enumerator":"1","resolved":true,"html_id":"id-7-col","remote":true,"url":"/colour-work-patterns","dataUrl":"/colour-work-patterns.json","key":"HGjBRG0YJQ"},{"type":"text","value":". Attempt 1 (left): R=2.4, r=0.8, w=h=0.4; Attempt 2 (right)  ","position":{"start":{"line":55,"column":1},"end":{"line":55,"column":1}},"key":"Dw78yD438S"},{"type":"inlineMath","value":"R = 2.4","position":{"start":{"line":55,"column":1},"end":{"line":55,"column":1}},"html":"<span class=\"katex\"><span class=\"katex-mathml\"><math xmlns=\"http://www.w3.org/1998/Math/MathML\"><semantics><mrow><mi>R</mi><mo>=</mo><mn>2.4</mn></mrow><annotation encoding=\"application/x-tex\">R = 2.4</annotation></semantics></math></span><span class=\"katex-html\" aria-hidden=\"true\"><span class=\"base\"><span class=\"strut\" style=\"height:0.6833em;\"></span><span class=\"mord mathnormal\" style=\"margin-right:0.00773em;\">R</span><span class=\"mspace\" style=\"margin-right:0.2778em;\"></span><span class=\"mrel\">=</span><span class=\"mspace\" style=\"margin-right:0.2778em;\"></span></span><span class=\"base\"><span class=\"strut\" style=\"height:0.6444em;\"></span><span class=\"mord\">2.4</span></span></span></span>","key":"JMPyEQF7ki"},{"type":"text","value":", ","position":{"start":{"line":55,"column":1},"end":{"line":55,"column":1}},"key":"TrbdbvycBo"},{"type":"inlineMath","value":"r = 0.8","position":{"start":{"line":55,"column":1},"end":{"line":55,"column":1}},"html":"<span class=\"katex\"><span class=\"katex-mathml\"><math xmlns=\"http://www.w3.org/1998/Math/MathML\"><semantics><mrow><mi>r</mi><mo>=</mo><mn>0.8</mn></mrow><annotation encoding=\"application/x-tex\">r = 0.8</annotation></semantics></math></span><span class=\"katex-html\" aria-hidden=\"true\"><span class=\"base\"><span class=\"strut\" style=\"height:0.4306em;\"></span><span class=\"mord mathnormal\" style=\"margin-right:0.02778em;\">r</span><span class=\"mspace\" style=\"margin-right:0.2778em;\"></span><span class=\"mrel\">=</span><span class=\"mspace\" style=\"margin-right:0.2778em;\"></span></span><span class=\"base\"><span class=\"strut\" style=\"height:0.6444em;\"></span><span class=\"mord\">0.8</span></span></span></span>","key":"VILTEDm7ds"},{"type":"text","value":", ","position":{"start":{"line":55,"column":1},"end":{"line":55,"column":1}},"key":"tV5NEtAeLs"},{"type":"inlineMath","value":"w = 0.48","position":{"start":{"line":55,"column":1},"end":{"line":55,"column":1}},"html":"<span class=\"katex\"><span class=\"katex-mathml\"><math xmlns=\"http://www.w3.org/1998/Math/MathML\"><semantics><mrow><mi>w</mi><mo>=</mo><mn>0.48</mn></mrow><annotation encoding=\"application/x-tex\">w = 0.48</annotation></semantics></math></span><span class=\"katex-html\" aria-hidden=\"true\"><span class=\"base\"><span class=\"strut\" style=\"height:0.4306em;\"></span><span class=\"mord mathnormal\" style=\"margin-right:0.02691em;\">w</span><span class=\"mspace\" style=\"margin-right:0.2778em;\"></span><span class=\"mrel\">=</span><span class=\"mspace\" style=\"margin-right:0.2778em;\"></span></span><span class=\"base\"><span class=\"strut\" style=\"height:0.6444em;\"></span><span class=\"mord\">0.48</span></span></span></span>","key":"WKoj4Pj5O1"},{"type":"text","value":", ","position":{"start":{"line":55,"column":1},"end":{"line":55,"column":1}},"key":"ujJN2FJfOs"},{"type":"inlineMath","value":"h=0.863","position":{"start":{"line":55,"column":1},"end":{"line":55,"column":1}},"html":"<span class=\"katex\"><span class=\"katex-mathml\"><math xmlns=\"http://www.w3.org/1998/Math/MathML\"><semantics><mrow><mi>h</mi><mo>=</mo><mn>0.863</mn></mrow><annotation encoding=\"application/x-tex\">h=0.863</annotation></semantics></math></span><span class=\"katex-html\" aria-hidden=\"true\"><span class=\"base\"><span class=\"strut\" style=\"height:0.6944em;\"></span><span class=\"mord mathnormal\">h</span><span class=\"mspace\" style=\"margin-right:0.2778em;\"></span><span class=\"mrel\">=</span><span class=\"mspace\" style=\"margin-right:0.2778em;\"></span></span><span class=\"base\"><span class=\"strut\" style=\"height:0.6444em;\"></span><span class=\"mord\">0.863</span></span></span></span>","key":"yEmltW49Ww"},{"type":"text","value":".","position":{"start":{"line":55,"column":1},"end":{"line":55,"column":1}},"key":"tzCLYEKRcf"}],"key":"bBoxYUrzr1"}],"key":"BfOdTWcE8X"}],"label":"fig:7-colour-2","identifier":"fig:7-colour-2","enumerator":"5","html_id":"fig-7-colour-2","key":"TrwFrojK2w"},{"type":"paragraph","position":{"start":{"line":58,"column":1},"end":{"line":58,"column":1}},"children":[{"type":"text","value":"Attempt 2 (right) resulted in a less distorted torus than Attempt 1 (left), and with more circular cross-sections. This illustrates the difficulty of measuring stitch dimensions from only one stitch. Better choices for w and h were calculated by measuring the two characteristic circumferences of the Attempt 1 crocheted torus and dividing by number of rows/stitches, as appropriate.","position":{"start":{"line":58,"column":1},"end":{"line":58,"column":1}},"key":"sxcw8tv1hZ"}],"key":"gn7VSJGXBy"},{"type":"heading","depth":3,"position":{"start":{"line":60,"column":1},"end":{"line":60,"column":1}},"children":[{"type":"text","value":"Feb 2026","position":{"start":{"line":60,"column":1},"end":{"line":60,"column":1}},"key":"dEOlPXort5"}],"identifier":"feb-2026","label":"Feb 2026","html_id":"feb-2026-1","implicit":true,"enumerator":"2.2","key":"vYSgzqayz1"},{"type":"container","kind":"figure","children":[{"type":"image","url":"/Feb26_torus_1-af0d00f8e720479776c76e292b1f27e5.jpg","alt":"R=4, r=1.6, w=0.4, h=0.4, N=20, \\frac{r\\pi}{N}=0.251<h","width":"400","data":{"altTextIsAutoGenerated":true},"key":"Fsthu7eM3Y","urlSource":"figs/Feb26_torus_1.jpg"},{"type":"caption","children":[{"type":"paragraph","position":{"start":{"line":64,"column":1},"end":{"line":64,"column":1}},"children":[{"type":"captionNumber","kind":"figure","label":"fig:Feb26_torus_1","identifier":"fig:feb26_torus_1","html_id":"fig-feb26-torus-1","enumerator":"6","children":[{"type":"text","value":"Figure ","key":"omtf7FiozK"},{"type":"text","value":"6","key":"xtKJ9qsFmG"},{"type":"text","value":":","key":"szYw3UeBt5"}],"template":"Figure %s:","key":"Ol5i4uKUVt"},{"type":"inlineMath","value":"R=4","position":{"start":{"line":64,"column":1},"end":{"line":64,"column":1}},"html":"<span class=\"katex\"><span class=\"katex-mathml\"><math xmlns=\"http://www.w3.org/1998/Math/MathML\"><semantics><mrow><mi>R</mi><mo>=</mo><mn>4</mn></mrow><annotation encoding=\"application/x-tex\">R=4</annotation></semantics></math></span><span class=\"katex-html\" aria-hidden=\"true\"><span class=\"base\"><span class=\"strut\" style=\"height:0.6833em;\"></span><span class=\"mord mathnormal\" style=\"margin-right:0.00773em;\">R</span><span class=\"mspace\" style=\"margin-right:0.2778em;\"></span><span class=\"mrel\">=</span><span class=\"mspace\" style=\"margin-right:0.2778em;\"></span></span><span class=\"base\"><span class=\"strut\" style=\"height:0.6444em;\"></span><span class=\"mord\">4</span></span></span></span>","key":"WlvOKtwY84"},{"type":"text","value":", ","position":{"start":{"line":64,"column":1},"end":{"line":64,"column":1}},"key":"ARUH84HIuq"},{"type":"inlineMath","value":"r=1.6","position":{"start":{"line":64,"column":1},"end":{"line":64,"column":1}},"html":"<span class=\"katex\"><span class=\"katex-mathml\"><math xmlns=\"http://www.w3.org/1998/Math/MathML\"><semantics><mrow><mi>r</mi><mo>=</mo><mn>1.6</mn></mrow><annotation encoding=\"application/x-tex\">r=1.6</annotation></semantics></math></span><span class=\"katex-html\" aria-hidden=\"true\"><span class=\"base\"><span class=\"strut\" style=\"height:0.4306em;\"></span><span class=\"mord mathnormal\" style=\"margin-right:0.02778em;\">r</span><span class=\"mspace\" style=\"margin-right:0.2778em;\"></span><span class=\"mrel\">=</span><span class=\"mspace\" style=\"margin-right:0.2778em;\"></span></span><span class=\"base\"><span class=\"strut\" style=\"height:0.6444em;\"></span><span class=\"mord\">1.6</span></span></span></span>","key":"Krt9I2JjE1"},{"type":"text","value":", ","position":{"start":{"line":64,"column":1},"end":{"line":64,"column":1}},"key":"zruyTxYFl3"},{"type":"inlineMath","value":"w=0.4","position":{"start":{"line":64,"column":1},"end":{"line":64,"column":1}},"html":"<span class=\"katex\"><span class=\"katex-mathml\"><math xmlns=\"http://www.w3.org/1998/Math/MathML\"><semantics><mrow><mi>w</mi><mo>=</mo><mn>0.4</mn></mrow><annotation encoding=\"application/x-tex\">w=0.4</annotation></semantics></math></span><span class=\"katex-html\" aria-hidden=\"true\"><span class=\"base\"><span class=\"strut\" style=\"height:0.4306em;\"></span><span class=\"mord mathnormal\" style=\"margin-right:0.02691em;\">w</span><span class=\"mspace\" style=\"margin-right:0.2778em;\"></span><span class=\"mrel\">=</span><span class=\"mspace\" style=\"margin-right:0.2778em;\"></span></span><span class=\"base\"><span class=\"strut\" style=\"height:0.6444em;\"></span><span class=\"mord\">0.4</span></span></span></span>","key":"KOQMCFrLO2"},{"type":"text","value":", ","position":{"start":{"line":64,"column":1},"end":{"line":64,"column":1}},"key":"qMTYog5eAi"},{"type":"inlineMath","value":"h=0.4","position":{"start":{"line":64,"column":1},"end":{"line":64,"column":1}},"html":"<span class=\"katex\"><span class=\"katex-mathml\"><math xmlns=\"http://www.w3.org/1998/Math/MathML\"><semantics><mrow><mi>h</mi><mo>=</mo><mn>0.4</mn></mrow><annotation encoding=\"application/x-tex\">h=0.4</annotation></semantics></math></span><span class=\"katex-html\" aria-hidden=\"true\"><span class=\"base\"><span class=\"strut\" style=\"height:0.6944em;\"></span><span class=\"mord mathnormal\">h</span><span class=\"mspace\" style=\"margin-right:0.2778em;\"></span><span class=\"mrel\">=</span><span class=\"mspace\" style=\"margin-right:0.2778em;\"></span></span><span class=\"base\"><span class=\"strut\" style=\"height:0.6444em;\"></span><span class=\"mord\">0.4</span></span></span></span>","key":"W8CjZlFM7J"},{"type":"text","value":", ","position":{"start":{"line":64,"column":1},"end":{"line":64,"column":1}},"key":"VI1DAYbGvZ"},{"type":"inlineMath","value":"N=20","position":{"start":{"line":64,"column":1},"end":{"line":64,"column":1}},"html":"<span class=\"katex\"><span class=\"katex-mathml\"><math xmlns=\"http://www.w3.org/1998/Math/MathML\"><semantics><mrow><mi>N</mi><mo>=</mo><mn>20</mn></mrow><annotation encoding=\"application/x-tex\">N=20</annotation></semantics></math></span><span class=\"katex-html\" aria-hidden=\"true\"><span class=\"base\"><span class=\"strut\" style=\"height:0.6833em;\"></span><span class=\"mord mathnormal\" style=\"margin-right:0.10903em;\">N</span><span class=\"mspace\" style=\"margin-right:0.2778em;\"></span><span class=\"mrel\">=</span><span class=\"mspace\" style=\"margin-right:0.2778em;\"></span></span><span class=\"base\"><span class=\"strut\" style=\"height:0.6444em;\"></span><span class=\"mord\">20</span></span></span></span>","key":"LAOQXAx5B0"},{"type":"text","value":", ","position":{"start":{"line":64,"column":1},"end":{"line":64,"column":1}},"key":"Rg4TpDDLuD"},{"type":"inlineMath","value":"\\frac{r\\pi}{N}=0.251<h","position":{"start":{"line":64,"column":1},"end":{"line":64,"column":1}},"html":"<span class=\"katex\"><span class=\"katex-mathml\"><math xmlns=\"http://www.w3.org/1998/Math/MathML\"><semantics><mrow><mfrac><mrow><mi>r</mi><mi>π</mi></mrow><mi>N</mi></mfrac><mo>=</mo><mn>0.251</mn><mo>&lt;</mo><mi>h</mi></mrow><annotation encoding=\"application/x-tex\">\\frac{r\\pi}{N}=0.251&lt;h</annotation></semantics></math></span><span class=\"katex-html\" aria-hidden=\"true\"><span class=\"base\"><span class=\"strut\" style=\"height:1.0404em;vertical-align:-0.345em;\"></span><span class=\"mord\"><span class=\"mopen nulldelimiter\"></span><span class=\"mfrac\"><span class=\"vlist-t vlist-t2\"><span class=\"vlist-r\"><span class=\"vlist\" style=\"height:0.6954em;\"><span style=\"top:-2.655em;\"><span class=\"pstrut\" style=\"height:3em;\"></span><span class=\"sizing reset-size6 size3 mtight\"><span class=\"mord mtight\"><span class=\"mord mathnormal mtight\" style=\"margin-right:0.10903em;\">N</span></span></span></span><span style=\"top:-3.23em;\"><span class=\"pstrut\" style=\"height:3em;\"></span><span class=\"frac-line\" style=\"border-bottom-width:0.04em;\"></span></span><span style=\"top:-3.394em;\"><span class=\"pstrut\" style=\"height:3em;\"></span><span class=\"sizing reset-size6 size3 mtight\"><span class=\"mord mtight\"><span class=\"mord mathnormal mtight\" style=\"margin-right:0.02778em;\">r</span><span class=\"mord mathnormal mtight\" style=\"margin-right:0.03588em;\">π</span></span></span></span></span><span class=\"vlist-s\">​</span></span><span class=\"vlist-r\"><span class=\"vlist\" style=\"height:0.345em;\"><span></span></span></span></span></span><span class=\"mclose nulldelimiter\"></span></span><span class=\"mspace\" style=\"margin-right:0.2778em;\"></span><span class=\"mrel\">=</span><span class=\"mspace\" style=\"margin-right:0.2778em;\"></span></span><span class=\"base\"><span class=\"strut\" style=\"height:0.6835em;vertical-align:-0.0391em;\"></span><span class=\"mord\">0.251</span><span class=\"mspace\" style=\"margin-right:0.2778em;\"></span><span class=\"mrel\">&lt;</span><span class=\"mspace\" style=\"margin-right:0.2778em;\"></span></span><span class=\"base\"><span class=\"strut\" style=\"height:0.6944em;\"></span><span class=\"mord mathnormal\">h</span></span></span></span>","key":"aEMp6iagvj"}],"key":"lu1wmwKOKQ"}],"key":"Vl8EgofXXW"}],"label":"fig:Feb26_torus_1","identifier":"fig:feb26_torus_1","enumerator":"6","html_id":"fig-feb26-torus-1","key":"hWw1t6STim"},{"type":"paragraph","position":{"start":{"line":67,"column":1},"end":{"line":67,"column":1}},"children":[{"type":"text","value":"This is a simple case of forgetting to update the row count, as I will still using a spreadsheet. ","position":{"start":{"line":67,"column":1},"end":{"line":67,"column":1}},"key":"ZoFLI2Ribt"},{"type":"inlineMath","value":"N=12","position":{"start":{"line":67,"column":1},"end":{"line":67,"column":1}},"html":"<span class=\"katex\"><span class=\"katex-mathml\"><math xmlns=\"http://www.w3.org/1998/Math/MathML\"><semantics><mrow><mi>N</mi><mo>=</mo><mn>12</mn></mrow><annotation encoding=\"application/x-tex\">N=12</annotation></semantics></math></span><span class=\"katex-html\" aria-hidden=\"true\"><span class=\"base\"><span class=\"strut\" style=\"height:0.6833em;\"></span><span class=\"mord mathnormal\" style=\"margin-right:0.10903em;\">N</span><span class=\"mspace\" style=\"margin-right:0.2778em;\"></span><span class=\"mrel\">=</span><span class=\"mspace\" style=\"margin-right:0.2778em;\"></span></span><span class=\"base\"><span class=\"strut\" style=\"height:0.6444em;\"></span><span class=\"mord\">12</span></span></span></span>","key":"AMNTxCtyFV"},{"type":"text","value":" or ","position":{"start":{"line":67,"column":1},"end":{"line":67,"column":1}},"key":"hOKBOpmSYF"},{"type":"inlineMath","value":"N=13","position":{"start":{"line":67,"column":1},"end":{"line":67,"column":1}},"html":"<span class=\"katex\"><span class=\"katex-mathml\"><math xmlns=\"http://www.w3.org/1998/Math/MathML\"><semantics><mrow><mi>N</mi><mo>=</mo><mn>13</mn></mrow><annotation encoding=\"application/x-tex\">N=13</annotation></semantics></math></span><span class=\"katex-html\" aria-hidden=\"true\"><span class=\"base\"><span class=\"strut\" style=\"height:0.6833em;\"></span><span class=\"mord mathnormal\" style=\"margin-right:0.10903em;\">N</span><span class=\"mspace\" style=\"margin-right:0.2778em;\"></span><span class=\"mrel\">=</span><span class=\"mspace\" style=\"margin-right:0.2778em;\"></span></span><span class=\"base\"><span class=\"strut\" style=\"height:0.6444em;\"></span><span class=\"mord\">13</span></span></span></span>","key":"pd6V72M8hZ"},{"type":"text","value":" would have worked better. I also suspect I mismeasured the stitch dimensions.","position":{"start":{"line":67,"column":1},"end":{"line":67,"column":1}},"key":"CcmpyAZ1LV"}],"key":"KTP0zoOlak"},{"type":"heading","depth":3,"position":{"start":{"line":69,"column":1},"end":{"line":69,"column":1}},"children":[{"type":"text","value":"Jan 2026","position":{"start":{"line":69,"column":1},"end":{"line":69,"column":1}},"key":"X2fvhnmkcc"}],"identifier":"jan-2026","label":"Jan 2026","html_id":"jan-2026","implicit":true,"enumerator":"2.3","key":"Nx2zbIVDwb"},{"type":"container","kind":"figure","children":[{"type":"image","url":"/Jan26_torus-3603dcd22bfca579e5da64708a735e36.jpg","alt":"R=4, r=1.6, w=0.4, h=0.35, N=20, \\frac{r\\pi}{N}=0.251<h","width":"400","data":{"altTextIsAutoGenerated":true},"key":"zPYOS0FTk1","urlSource":"figs/Jan26_torus.jpg"},{"type":"caption","children":[{"type":"paragraph","position":{"start":{"line":74,"column":1},"end":{"line":74,"column":1}},"children":[{"type":"captionNumber","kind":"figure","label":"fig:Jan26_torus","identifier":"fig:jan26_torus","html_id":"fig-jan26-torus","enumerator":"7","children":[{"type":"text","value":"Figure ","key":"X88jvmCd4R"},{"type":"text","value":"7","key":"yVmYIJLtEr"},{"type":"text","value":":","key":"NYhibuNev9"}],"template":"Figure %s:","key":"rdfPHXAsVW"},{"type":"inlineMath","value":"R=4","position":{"start":{"line":74,"column":1},"end":{"line":74,"column":1}},"html":"<span class=\"katex\"><span class=\"katex-mathml\"><math xmlns=\"http://www.w3.org/1998/Math/MathML\"><semantics><mrow><mi>R</mi><mo>=</mo><mn>4</mn></mrow><annotation encoding=\"application/x-tex\">R=4</annotation></semantics></math></span><span class=\"katex-html\" aria-hidden=\"true\"><span class=\"base\"><span class=\"strut\" style=\"height:0.6833em;\"></span><span class=\"mord mathnormal\" style=\"margin-right:0.00773em;\">R</span><span class=\"mspace\" style=\"margin-right:0.2778em;\"></span><span class=\"mrel\">=</span><span class=\"mspace\" style=\"margin-right:0.2778em;\"></span></span><span class=\"base\"><span class=\"strut\" style=\"height:0.6444em;\"></span><span class=\"mord\">4</span></span></span></span>","key":"pibpebhuIy"},{"type":"text","value":", ","position":{"start":{"line":74,"column":1},"end":{"line":74,"column":1}},"key":"GSv8mK630i"},{"type":"inlineMath","value":"r=1.6","position":{"start":{"line":74,"column":1},"end":{"line":74,"column":1}},"html":"<span class=\"katex\"><span class=\"katex-mathml\"><math xmlns=\"http://www.w3.org/1998/Math/MathML\"><semantics><mrow><mi>r</mi><mo>=</mo><mn>1.6</mn></mrow><annotation encoding=\"application/x-tex\">r=1.6</annotation></semantics></math></span><span class=\"katex-html\" aria-hidden=\"true\"><span class=\"base\"><span class=\"strut\" style=\"height:0.4306em;\"></span><span class=\"mord mathnormal\" style=\"margin-right:0.02778em;\">r</span><span class=\"mspace\" style=\"margin-right:0.2778em;\"></span><span class=\"mrel\">=</span><span class=\"mspace\" style=\"margin-right:0.2778em;\"></span></span><span class=\"base\"><span class=\"strut\" style=\"height:0.6444em;\"></span><span class=\"mord\">1.6</span></span></span></span>","key":"gvioUhTp9K"},{"type":"text","value":", ","position":{"start":{"line":74,"column":1},"end":{"line":74,"column":1}},"key":"KnQ92wbkic"},{"type":"inlineMath","value":"w=0.4","position":{"start":{"line":74,"column":1},"end":{"line":74,"column":1}},"html":"<span class=\"katex\"><span class=\"katex-mathml\"><math xmlns=\"http://www.w3.org/1998/Math/MathML\"><semantics><mrow><mi>w</mi><mo>=</mo><mn>0.4</mn></mrow><annotation encoding=\"application/x-tex\">w=0.4</annotation></semantics></math></span><span class=\"katex-html\" aria-hidden=\"true\"><span class=\"base\"><span class=\"strut\" style=\"height:0.4306em;\"></span><span class=\"mord mathnormal\" style=\"margin-right:0.02691em;\">w</span><span class=\"mspace\" style=\"margin-right:0.2778em;\"></span><span class=\"mrel\">=</span><span class=\"mspace\" style=\"margin-right:0.2778em;\"></span></span><span class=\"base\"><span class=\"strut\" style=\"height:0.6444em;\"></span><span class=\"mord\">0.4</span></span></span></span>","key":"Go5W2X3ben"},{"type":"text","value":", ","position":{"start":{"line":74,"column":1},"end":{"line":74,"column":1}},"key":"c76DuFydM8"},{"type":"inlineMath","value":"h=0.35","position":{"start":{"line":74,"column":1},"end":{"line":74,"column":1}},"html":"<span class=\"katex\"><span class=\"katex-mathml\"><math xmlns=\"http://www.w3.org/1998/Math/MathML\"><semantics><mrow><mi>h</mi><mo>=</mo><mn>0.35</mn></mrow><annotation encoding=\"application/x-tex\">h=0.35</annotation></semantics></math></span><span class=\"katex-html\" aria-hidden=\"true\"><span class=\"base\"><span class=\"strut\" style=\"height:0.6944em;\"></span><span class=\"mord mathnormal\">h</span><span class=\"mspace\" style=\"margin-right:0.2778em;\"></span><span class=\"mrel\">=</span><span class=\"mspace\" style=\"margin-right:0.2778em;\"></span></span><span class=\"base\"><span class=\"strut\" style=\"height:0.6444em;\"></span><span class=\"mord\">0.35</span></span></span></span>","key":"NLwNobTqqH"},{"type":"text","value":", ","position":{"start":{"line":74,"column":1},"end":{"line":74,"column":1}},"key":"opw12Jt69d"},{"type":"inlineMath","value":"N=20","position":{"start":{"line":74,"column":1},"end":{"line":74,"column":1}},"html":"<span class=\"katex\"><span class=\"katex-mathml\"><math xmlns=\"http://www.w3.org/1998/Math/MathML\"><semantics><mrow><mi>N</mi><mo>=</mo><mn>20</mn></mrow><annotation encoding=\"application/x-tex\">N=20</annotation></semantics></math></span><span class=\"katex-html\" aria-hidden=\"true\"><span class=\"base\"><span class=\"strut\" style=\"height:0.6833em;\"></span><span class=\"mord mathnormal\" style=\"margin-right:0.10903em;\">N</span><span class=\"mspace\" style=\"margin-right:0.2778em;\"></span><span class=\"mrel\">=</span><span class=\"mspace\" style=\"margin-right:0.2778em;\"></span></span><span class=\"base\"><span class=\"strut\" style=\"height:0.6444em;\"></span><span class=\"mord\">20</span></span></span></span>","key":"YPfiRnEFej"},{"type":"text","value":", ","position":{"start":{"line":74,"column":1},"end":{"line":74,"column":1}},"key":"cLTptmpV4f"},{"type":"inlineMath","value":"\\frac{r\\pi}{N}=0.251<h","position":{"start":{"line":74,"column":1},"end":{"line":74,"column":1}},"html":"<span class=\"katex\"><span class=\"katex-mathml\"><math xmlns=\"http://www.w3.org/1998/Math/MathML\"><semantics><mrow><mfrac><mrow><mi>r</mi><mi>π</mi></mrow><mi>N</mi></mfrac><mo>=</mo><mn>0.251</mn><mo>&lt;</mo><mi>h</mi></mrow><annotation encoding=\"application/x-tex\">\\frac{r\\pi}{N}=0.251&lt;h</annotation></semantics></math></span><span class=\"katex-html\" aria-hidden=\"true\"><span class=\"base\"><span class=\"strut\" style=\"height:1.0404em;vertical-align:-0.345em;\"></span><span class=\"mord\"><span class=\"mopen nulldelimiter\"></span><span class=\"mfrac\"><span class=\"vlist-t vlist-t2\"><span class=\"vlist-r\"><span class=\"vlist\" style=\"height:0.6954em;\"><span style=\"top:-2.655em;\"><span class=\"pstrut\" style=\"height:3em;\"></span><span class=\"sizing reset-size6 size3 mtight\"><span class=\"mord mtight\"><span class=\"mord mathnormal mtight\" style=\"margin-right:0.10903em;\">N</span></span></span></span><span style=\"top:-3.23em;\"><span class=\"pstrut\" style=\"height:3em;\"></span><span class=\"frac-line\" style=\"border-bottom-width:0.04em;\"></span></span><span style=\"top:-3.394em;\"><span class=\"pstrut\" style=\"height:3em;\"></span><span class=\"sizing reset-size6 size3 mtight\"><span class=\"mord mtight\"><span class=\"mord mathnormal mtight\" style=\"margin-right:0.02778em;\">r</span><span class=\"mord mathnormal mtight\" style=\"margin-right:0.03588em;\">π</span></span></span></span></span><span class=\"vlist-s\">​</span></span><span class=\"vlist-r\"><span class=\"vlist\" style=\"height:0.345em;\"><span></span></span></span></span></span><span class=\"mclose nulldelimiter\"></span></span><span class=\"mspace\" style=\"margin-right:0.2778em;\"></span><span class=\"mrel\">=</span><span class=\"mspace\" style=\"margin-right:0.2778em;\"></span></span><span class=\"base\"><span class=\"strut\" style=\"height:0.6835em;vertical-align:-0.0391em;\"></span><span class=\"mord\">0.251</span><span class=\"mspace\" style=\"margin-right:0.2778em;\"></span><span class=\"mrel\">&lt;</span><span class=\"mspace\" style=\"margin-right:0.2778em;\"></span></span><span class=\"base\"><span class=\"strut\" style=\"height:0.6944em;\"></span><span class=\"mord mathnormal\">h</span></span></span></span>","key":"IdmXn6e8Ky"}],"key":"qLkIT3WAN8"}],"key":"DM983IAaT7"}],"label":"fig:Jan26_torus","identifier":"fig:jan26_torus","enumerator":"7","html_id":"fig-jan26-torus","key":"Il838Rhv1d"},{"type":"paragraph","position":{"start":{"line":77,"column":1},"end":{"line":77,"column":1}},"children":[{"type":"text","value":"Again, too many rows for the stitch dimensions. However, it is less noticeable than in ","position":{"start":{"line":77,"column":1},"end":{"line":77,"column":1}},"key":"tIb9XWk6Fq"},{"type":"crossReference","position":{"start":{"line":77,"column":1},"end":{"line":77,"column":1}},"children":[{"type":"text","value":"Figure ","key":"FIlKNA2c9f"},{"type":"text","value":"6","key":"nAwVmcNdrm"}],"identifier":"fig:feb26_torus_1","label":"fig:Feb26_torus_1","kind":"figure","template":"Figure %s","enumerator":"6","resolved":true,"html_id":"fig-feb26-torus-1","key":"EbcCwckHKA"},{"type":"text","value":", since the stitch height is smaller.","position":{"start":{"line":77,"column":1},"end":{"line":77,"column":1}},"key":"i1E3QaNcL2"}],"key":"sSYbR1wRBd"},{"type":"paragraph","position":{"start":{"line":79,"column":1},"end":{"line":79,"column":1}},"children":[{"type":"text","value":"The triangulation has 12 vertices, as this is what would be needed for the classical tonnetz (of pitch classes). Below is a diagram I used to create it. Eventually I will make a crochet pattern that directly incorporates it via stitch colouring.","position":{"start":{"line":79,"column":1},"end":{"line":79,"column":1}},"key":"hjOXngCbOB"}],"key":"GFvcEhatBU"},{"type":"container","kind":"figure","children":[{"type":"image","url":"/tonnetz-grid-e73d9f837955fc163e50b007367ea2a9.png","alt":"Tonnetz triangulation.","width":"400","data":{"altTextIsAutoGenerated":true},"key":"quzAsCgxRQ","urlSource":"figs/tonnetz-grid.png"},{"type":"caption","children":[{"type":"paragraph","position":{"start":{"line":85,"column":1},"end":{"line":85,"column":1}},"children":[{"type":"captionNumber","kind":"figure","label":"fig:tonnetz-grid","identifier":"fig:tonnetz-grid","html_id":"fig-tonnetz-grid","enumerator":"8","children":[{"type":"text","value":"Figure ","key":"XZYVFJqkEB"},{"type":"text","value":"8","key":"lsllTyy7QE"},{"type":"text","value":":","key":"yrfSNDT2oo"}],"template":"Figure %s:","key":"lyDb5shVGc"},{"type":"text","value":"Tonnetz triangulation.","position":{"start":{"line":85,"column":1},"end":{"line":85,"column":1}},"key":"V6asUhj4lq"}],"key":"r4PHPJEiNI"}],"key":"tXqhiWX6a4"}],"label":"fig:tonnetz-grid","identifier":"fig:tonnetz-grid","enumerator":"8","html_id":"fig-tonnetz-grid","key":"PtdsGFPqIj"},{"type":"paragraph","position":{"start":{"line":88,"column":1},"end":{"line":88,"column":1}},"children":[{"type":"link","url":"https://thetonnetz.com/","position":{"start":{"line":88,"column":1},"end":{"line":88,"column":1}},"children":[{"type":"text","value":"Here is a nice web app for investigating  tonnetze.","position":{"start":{"line":88,"column":1},"end":{"line":88,"column":1}},"key":"dfh0yTESPW"}],"urlSource":"https://thetonnetz.com/","key":"tRXxZp6tIt"}],"key":"Diixvb5HP0"},{"type":"heading","depth":3,"position":{"start":{"line":90,"column":1},"end":{"line":90,"column":1}},"children":[{"type":"text","value":"Sept 2025","position":{"start":{"line":90,"column":1},"end":{"line":90,"column":1}},"key":"i4eBNCJy9f"}],"identifier":"sept-2025","label":"Sept 2025","html_id":"sept-2025-1","implicit":true,"enumerator":"2.4","key":"eHZx1zv7oV"},{"type":"container","kind":"figure","children":[{"type":"image","url":"/Sept25_torus_1-6d792a5250338ee5605b2b17e86857c0.jpg","alt":"Sept 2025: R=2, r=1, w=0.52, h=0.82, N=10, \\frac{r\\pi}{N}=0.314<h","width":"400","data":{"altTextIsAutoGenerated":true},"key":"DseicdmNfh","urlSource":"figs/Sept25_torus_1.jpg"},{"type":"caption","children":[{"type":"paragraph","position":{"start":{"line":95,"column":1},"end":{"line":95,"column":1}},"children":[{"type":"captionNumber","kind":"figure","label":"fig:Sept25_torus_1","identifier":"fig:sept25_torus_1","html_id":"fig-sept25-torus-1","enumerator":"9","children":[{"type":"text","value":"Figure ","key":"DBjEDOeiGv"},{"type":"text","value":"9","key":"PlE4dLOuPd"},{"type":"text","value":":","key":"QHI8mSU52g"}],"template":"Figure %s:","key":"qTm90bU0kX"},{"type":"text","value":"Sept 2025: ","position":{"start":{"line":95,"column":1},"end":{"line":95,"column":1}},"key":"aAwIaL6FBQ"},{"type":"inlineMath","value":"R=2","position":{"start":{"line":95,"column":1},"end":{"line":95,"column":1}},"html":"<span class=\"katex\"><span class=\"katex-mathml\"><math xmlns=\"http://www.w3.org/1998/Math/MathML\"><semantics><mrow><mi>R</mi><mo>=</mo><mn>2</mn></mrow><annotation encoding=\"application/x-tex\">R=2</annotation></semantics></math></span><span class=\"katex-html\" aria-hidden=\"true\"><span class=\"base\"><span class=\"strut\" style=\"height:0.6833em;\"></span><span class=\"mord mathnormal\" style=\"margin-right:0.00773em;\">R</span><span class=\"mspace\" style=\"margin-right:0.2778em;\"></span><span class=\"mrel\">=</span><span class=\"mspace\" style=\"margin-right:0.2778em;\"></span></span><span class=\"base\"><span class=\"strut\" style=\"height:0.6444em;\"></span><span class=\"mord\">2</span></span></span></span>","key":"pLrV6LSkF3"},{"type":"text","value":", ","position":{"start":{"line":95,"column":1},"end":{"line":95,"column":1}},"key":"APRDBRlyBJ"},{"type":"inlineMath","value":"r=1","position":{"start":{"line":95,"column":1},"end":{"line":95,"column":1}},"html":"<span class=\"katex\"><span class=\"katex-mathml\"><math xmlns=\"http://www.w3.org/1998/Math/MathML\"><semantics><mrow><mi>r</mi><mo>=</mo><mn>1</mn></mrow><annotation encoding=\"application/x-tex\">r=1</annotation></semantics></math></span><span class=\"katex-html\" aria-hidden=\"true\"><span class=\"base\"><span class=\"strut\" style=\"height:0.4306em;\"></span><span class=\"mord mathnormal\" style=\"margin-right:0.02778em;\">r</span><span class=\"mspace\" style=\"margin-right:0.2778em;\"></span><span class=\"mrel\">=</span><span class=\"mspace\" style=\"margin-right:0.2778em;\"></span></span><span class=\"base\"><span class=\"strut\" style=\"height:0.6444em;\"></span><span class=\"mord\">1</span></span></span></span>","key":"GZnyAMWWfL"},{"type":"text","value":", ","position":{"start":{"line":95,"column":1},"end":{"line":95,"column":1}},"key":"D04YERbbkR"},{"type":"inlineMath","value":"w=0.52","position":{"start":{"line":95,"column":1},"end":{"line":95,"column":1}},"html":"<span class=\"katex\"><span class=\"katex-mathml\"><math xmlns=\"http://www.w3.org/1998/Math/MathML\"><semantics><mrow><mi>w</mi><mo>=</mo><mn>0.52</mn></mrow><annotation encoding=\"application/x-tex\">w=0.52</annotation></semantics></math></span><span class=\"katex-html\" aria-hidden=\"true\"><span class=\"base\"><span class=\"strut\" style=\"height:0.4306em;\"></span><span class=\"mord mathnormal\" style=\"margin-right:0.02691em;\">w</span><span class=\"mspace\" style=\"margin-right:0.2778em;\"></span><span class=\"mrel\">=</span><span class=\"mspace\" style=\"margin-right:0.2778em;\"></span></span><span class=\"base\"><span class=\"strut\" style=\"height:0.6444em;\"></span><span class=\"mord\">0.52</span></span></span></span>","key":"jpl2JmiKTx"},{"type":"text","value":", ","position":{"start":{"line":95,"column":1},"end":{"line":95,"column":1}},"key":"jTp1uyfUTn"},{"type":"inlineMath","value":"h=0.82","position":{"start":{"line":95,"column":1},"end":{"line":95,"column":1}},"html":"<span class=\"katex\"><span class=\"katex-mathml\"><math xmlns=\"http://www.w3.org/1998/Math/MathML\"><semantics><mrow><mi>h</mi><mo>=</mo><mn>0.82</mn></mrow><annotation encoding=\"application/x-tex\">h=0.82</annotation></semantics></math></span><span class=\"katex-html\" aria-hidden=\"true\"><span class=\"base\"><span class=\"strut\" style=\"height:0.6944em;\"></span><span class=\"mord mathnormal\">h</span><span class=\"mspace\" style=\"margin-right:0.2778em;\"></span><span class=\"mrel\">=</span><span class=\"mspace\" style=\"margin-right:0.2778em;\"></span></span><span class=\"base\"><span class=\"strut\" style=\"height:0.6444em;\"></span><span class=\"mord\">0.82</span></span></span></span>","key":"UJq224DkPs"},{"type":"text","value":", ","position":{"start":{"line":95,"column":1},"end":{"line":95,"column":1}},"key":"pUEr4zPKKa"},{"type":"inlineMath","value":"N=10","position":{"start":{"line":95,"column":1},"end":{"line":95,"column":1}},"html":"<span class=\"katex\"><span class=\"katex-mathml\"><math xmlns=\"http://www.w3.org/1998/Math/MathML\"><semantics><mrow><mi>N</mi><mo>=</mo><mn>10</mn></mrow><annotation encoding=\"application/x-tex\">N=10</annotation></semantics></math></span><span class=\"katex-html\" aria-hidden=\"true\"><span class=\"base\"><span class=\"strut\" style=\"height:0.6833em;\"></span><span class=\"mord mathnormal\" style=\"margin-right:0.10903em;\">N</span><span class=\"mspace\" style=\"margin-right:0.2778em;\"></span><span class=\"mrel\">=</span><span class=\"mspace\" style=\"margin-right:0.2778em;\"></span></span><span class=\"base\"><span class=\"strut\" style=\"height:0.6444em;\"></span><span class=\"mord\">10</span></span></span></span>","key":"Um2Mz0kEyB"},{"type":"text","value":", ","position":{"start":{"line":95,"column":1},"end":{"line":95,"column":1}},"key":"fXulCQncQD"},{"type":"inlineMath","value":"\\frac{r\\pi}{N}=0.314<h","position":{"start":{"line":95,"column":1},"end":{"line":95,"column":1}},"html":"<span class=\"katex\"><span class=\"katex-mathml\"><math xmlns=\"http://www.w3.org/1998/Math/MathML\"><semantics><mrow><mfrac><mrow><mi>r</mi><mi>π</mi></mrow><mi>N</mi></mfrac><mo>=</mo><mn>0.314</mn><mo>&lt;</mo><mi>h</mi></mrow><annotation encoding=\"application/x-tex\">\\frac{r\\pi}{N}=0.314&lt;h</annotation></semantics></math></span><span class=\"katex-html\" aria-hidden=\"true\"><span class=\"base\"><span class=\"strut\" style=\"height:1.0404em;vertical-align:-0.345em;\"></span><span class=\"mord\"><span class=\"mopen nulldelimiter\"></span><span class=\"mfrac\"><span class=\"vlist-t vlist-t2\"><span class=\"vlist-r\"><span class=\"vlist\" style=\"height:0.6954em;\"><span style=\"top:-2.655em;\"><span class=\"pstrut\" style=\"height:3em;\"></span><span class=\"sizing reset-size6 size3 mtight\"><span class=\"mord mtight\"><span class=\"mord mathnormal mtight\" style=\"margin-right:0.10903em;\">N</span></span></span></span><span style=\"top:-3.23em;\"><span class=\"pstrut\" style=\"height:3em;\"></span><span class=\"frac-line\" style=\"border-bottom-width:0.04em;\"></span></span><span style=\"top:-3.394em;\"><span class=\"pstrut\" style=\"height:3em;\"></span><span class=\"sizing reset-size6 size3 mtight\"><span class=\"mord mtight\"><span class=\"mord mathnormal mtight\" style=\"margin-right:0.02778em;\">r</span><span class=\"mord mathnormal mtight\" style=\"margin-right:0.03588em;\">π</span></span></span></span></span><span class=\"vlist-s\">​</span></span><span class=\"vlist-r\"><span class=\"vlist\" style=\"height:0.345em;\"><span></span></span></span></span></span><span class=\"mclose nulldelimiter\"></span></span><span class=\"mspace\" style=\"margin-right:0.2778em;\"></span><span class=\"mrel\">=</span><span class=\"mspace\" style=\"margin-right:0.2778em;\"></span></span><span class=\"base\"><span class=\"strut\" style=\"height:0.6835em;vertical-align:-0.0391em;\"></span><span class=\"mord\">0.314</span><span class=\"mspace\" style=\"margin-right:0.2778em;\"></span><span class=\"mrel\">&lt;</span><span class=\"mspace\" style=\"margin-right:0.2778em;\"></span></span><span class=\"base\"><span class=\"strut\" style=\"height:0.6944em;\"></span><span class=\"mord mathnormal\">h</span></span></span></span>","key":"mnOi9gY3sC"}],"key":"UnpGpwddOW"}],"key":"zv2XQGHqHZ"}],"label":"fig:Sept25_torus_1","identifier":"fig:sept25_torus_1","enumerator":"9","html_id":"fig-sept25-torus-1","key":"nJe4RAjU7g"},{"type":"paragraph","position":{"start":{"line":98,"column":1},"end":{"line":98,"column":1}},"children":[{"type":"text","value":"Too many rows for the stitch dimensions, and some serious mismeasurement (e.g. stitch width in reality is closer to ","position":{"start":{"line":98,"column":1},"end":{"line":98,"column":1}},"key":"YV1jZMqGLn"},{"type":"text","value":"0.7","position":{"start":{"line":98,"column":1},"end":{"line":98,"column":1}},"key":"AtWnakpEEd"},{"type":"text","value":").","position":{"start":{"line":98,"column":1},"end":{"line":98,"column":1}},"key":"CXqO1OnOsG"}],"key":"UwDLDNPSlS"},{"type":"heading","depth":3,"position":{"start":{"line":100,"column":1},"end":{"line":100,"column":1}},"children":[{"type":"text","value":"June 2025","position":{"start":{"line":100,"column":1},"end":{"line":100,"column":1}},"key":"sj1Y04OGsy"}],"identifier":"june-2025","label":"June 2025","html_id":"june-2025","implicit":true,"enumerator":"2.5","key":"sGAUxt5UwA"},{"type":"container","kind":"figure","children":[{"type":"image","url":"/June25_torus-80adec5c397e7fee86e1e50d9151946f.jpg","alt":"June 2025: R=3, r=1, w=0.52, h=0.65, N=10, \\frac{r\\pi}{N}=0.314<h.","width":"400","data":{"altTextIsAutoGenerated":true},"key":"MMLe8xPfjC","urlSource":"figs/June25_torus.jpg"},{"type":"caption","children":[{"type":"paragraph","position":{"start":{"line":105,"column":1},"end":{"line":105,"column":1}},"children":[{"type":"captionNumber","kind":"figure","label":"fig:June25_torus","identifier":"fig:june25_torus","html_id":"fig-june25-torus","enumerator":"10","children":[{"type":"text","value":"Figure ","key":"N114vs4d1x"},{"type":"text","value":"10","key":"Je7SuL1iWu"},{"type":"text","value":":","key":"G149wm38Xs"}],"template":"Figure %s:","key":"tqbtHbJ9IM"},{"type":"text","value":"June 2025: ","position":{"start":{"line":105,"column":1},"end":{"line":105,"column":1}},"key":"RlFGlRfmlE"},{"type":"inlineMath","value":"R=3","position":{"start":{"line":105,"column":1},"end":{"line":105,"column":1}},"html":"<span class=\"katex\"><span class=\"katex-mathml\"><math xmlns=\"http://www.w3.org/1998/Math/MathML\"><semantics><mrow><mi>R</mi><mo>=</mo><mn>3</mn></mrow><annotation encoding=\"application/x-tex\">R=3</annotation></semantics></math></span><span class=\"katex-html\" aria-hidden=\"true\"><span class=\"base\"><span class=\"strut\" style=\"height:0.6833em;\"></span><span class=\"mord mathnormal\" style=\"margin-right:0.00773em;\">R</span><span class=\"mspace\" style=\"margin-right:0.2778em;\"></span><span class=\"mrel\">=</span><span class=\"mspace\" style=\"margin-right:0.2778em;\"></span></span><span class=\"base\"><span class=\"strut\" style=\"height:0.6444em;\"></span><span class=\"mord\">3</span></span></span></span>","key":"R0Pcl3PQi4"},{"type":"text","value":", ","position":{"start":{"line":105,"column":1},"end":{"line":105,"column":1}},"key":"YJpsVgZpBH"},{"type":"inlineMath","value":"r=1","position":{"start":{"line":105,"column":1},"end":{"line":105,"column":1}},"html":"<span class=\"katex\"><span class=\"katex-mathml\"><math xmlns=\"http://www.w3.org/1998/Math/MathML\"><semantics><mrow><mi>r</mi><mo>=</mo><mn>1</mn></mrow><annotation encoding=\"application/x-tex\">r=1</annotation></semantics></math></span><span class=\"katex-html\" aria-hidden=\"true\"><span class=\"base\"><span class=\"strut\" style=\"height:0.4306em;\"></span><span class=\"mord mathnormal\" style=\"margin-right:0.02778em;\">r</span><span class=\"mspace\" style=\"margin-right:0.2778em;\"></span><span class=\"mrel\">=</span><span class=\"mspace\" style=\"margin-right:0.2778em;\"></span></span><span class=\"base\"><span class=\"strut\" style=\"height:0.6444em;\"></span><span class=\"mord\">1</span></span></span></span>","key":"J4ZxOlxn0Q"},{"type":"text","value":", ","position":{"start":{"line":105,"column":1},"end":{"line":105,"column":1}},"key":"CZpQu2RmaB"},{"type":"inlineMath","value":"w=0.52","position":{"start":{"line":105,"column":1},"end":{"line":105,"column":1}},"html":"<span class=\"katex\"><span class=\"katex-mathml\"><math xmlns=\"http://www.w3.org/1998/Math/MathML\"><semantics><mrow><mi>w</mi><mo>=</mo><mn>0.52</mn></mrow><annotation encoding=\"application/x-tex\">w=0.52</annotation></semantics></math></span><span class=\"katex-html\" aria-hidden=\"true\"><span class=\"base\"><span class=\"strut\" style=\"height:0.4306em;\"></span><span class=\"mord mathnormal\" style=\"margin-right:0.02691em;\">w</span><span class=\"mspace\" style=\"margin-right:0.2778em;\"></span><span class=\"mrel\">=</span><span class=\"mspace\" style=\"margin-right:0.2778em;\"></span></span><span class=\"base\"><span class=\"strut\" style=\"height:0.6444em;\"></span><span class=\"mord\">0.52</span></span></span></span>","key":"DPCLRWEUPO"},{"type":"text","value":", ","position":{"start":{"line":105,"column":1},"end":{"line":105,"column":1}},"key":"pz9vz5OVgX"},{"type":"inlineMath","value":"h=0.65","position":{"start":{"line":105,"column":1},"end":{"line":105,"column":1}},"html":"<span class=\"katex\"><span class=\"katex-mathml\"><math xmlns=\"http://www.w3.org/1998/Math/MathML\"><semantics><mrow><mi>h</mi><mo>=</mo><mn>0.65</mn></mrow><annotation encoding=\"application/x-tex\">h=0.65</annotation></semantics></math></span><span class=\"katex-html\" aria-hidden=\"true\"><span class=\"base\"><span class=\"strut\" style=\"height:0.6944em;\"></span><span class=\"mord mathnormal\">h</span><span class=\"mspace\" style=\"margin-right:0.2778em;\"></span><span class=\"mrel\">=</span><span class=\"mspace\" style=\"margin-right:0.2778em;\"></span></span><span class=\"base\"><span class=\"strut\" style=\"height:0.6444em;\"></span><span class=\"mord\">0.65</span></span></span></span>","key":"tOcBEtzf5k"},{"type":"text","value":", ","position":{"start":{"line":105,"column":1},"end":{"line":105,"column":1}},"key":"NcoC3dNZQa"},{"type":"inlineMath","value":"N=10","position":{"start":{"line":105,"column":1},"end":{"line":105,"column":1}},"html":"<span class=\"katex\"><span class=\"katex-mathml\"><math xmlns=\"http://www.w3.org/1998/Math/MathML\"><semantics><mrow><mi>N</mi><mo>=</mo><mn>10</mn></mrow><annotation encoding=\"application/x-tex\">N=10</annotation></semantics></math></span><span class=\"katex-html\" aria-hidden=\"true\"><span class=\"base\"><span class=\"strut\" style=\"height:0.6833em;\"></span><span class=\"mord mathnormal\" style=\"margin-right:0.10903em;\">N</span><span class=\"mspace\" style=\"margin-right:0.2778em;\"></span><span class=\"mrel\">=</span><span class=\"mspace\" style=\"margin-right:0.2778em;\"></span></span><span class=\"base\"><span class=\"strut\" style=\"height:0.6444em;\"></span><span class=\"mord\">10</span></span></span></span>","key":"p5saGkK7ow"},{"type":"text","value":", ","position":{"start":{"line":105,"column":1},"end":{"line":105,"column":1}},"key":"QMC1M1Z0zf"},{"type":"inlineMath","value":"\\frac{r\\pi}{N}=0.314<h","position":{"start":{"line":105,"column":1},"end":{"line":105,"column":1}},"html":"<span class=\"katex\"><span class=\"katex-mathml\"><math xmlns=\"http://www.w3.org/1998/Math/MathML\"><semantics><mrow><mfrac><mrow><mi>r</mi><mi>π</mi></mrow><mi>N</mi></mfrac><mo>=</mo><mn>0.314</mn><mo>&lt;</mo><mi>h</mi></mrow><annotation encoding=\"application/x-tex\">\\frac{r\\pi}{N}=0.314&lt;h</annotation></semantics></math></span><span class=\"katex-html\" aria-hidden=\"true\"><span class=\"base\"><span class=\"strut\" style=\"height:1.0404em;vertical-align:-0.345em;\"></span><span class=\"mord\"><span class=\"mopen nulldelimiter\"></span><span class=\"mfrac\"><span class=\"vlist-t vlist-t2\"><span class=\"vlist-r\"><span class=\"vlist\" style=\"height:0.6954em;\"><span style=\"top:-2.655em;\"><span class=\"pstrut\" style=\"height:3em;\"></span><span class=\"sizing reset-size6 size3 mtight\"><span class=\"mord mtight\"><span class=\"mord mathnormal mtight\" style=\"margin-right:0.10903em;\">N</span></span></span></span><span style=\"top:-3.23em;\"><span class=\"pstrut\" style=\"height:3em;\"></span><span class=\"frac-line\" style=\"border-bottom-width:0.04em;\"></span></span><span style=\"top:-3.394em;\"><span class=\"pstrut\" style=\"height:3em;\"></span><span class=\"sizing reset-size6 size3 mtight\"><span class=\"mord mtight\"><span class=\"mord mathnormal mtight\" style=\"margin-right:0.02778em;\">r</span><span class=\"mord mathnormal mtight\" style=\"margin-right:0.03588em;\">π</span></span></span></span></span><span class=\"vlist-s\">​</span></span><span class=\"vlist-r\"><span class=\"vlist\" style=\"height:0.345em;\"><span></span></span></span></span></span><span class=\"mclose nulldelimiter\"></span></span><span class=\"mspace\" style=\"margin-right:0.2778em;\"></span><span class=\"mrel\">=</span><span class=\"mspace\" style=\"margin-right:0.2778em;\"></span></span><span class=\"base\"><span class=\"strut\" style=\"height:0.6835em;vertical-align:-0.0391em;\"></span><span class=\"mord\">0.314</span><span class=\"mspace\" style=\"margin-right:0.2778em;\"></span><span class=\"mrel\">&lt;</span><span class=\"mspace\" style=\"margin-right:0.2778em;\"></span></span><span class=\"base\"><span class=\"strut\" style=\"height:0.6944em;\"></span><span class=\"mord mathnormal\">h</span></span></span></span>","key":"wgXbD0yGoR"},{"type":"text","value":".","position":{"start":{"line":105,"column":1},"end":{"line":105,"column":1}},"key":"dUgekdrmDV"}],"key":"AOE1zjT5QR"}],"key":"Z0DiCiQb4w"}],"label":"fig:June25_torus","identifier":"fig:june25_torus","enumerator":"10","html_id":"fig-june25-torus","key":"R6O2nGc6tm"},{"type":"paragraph","position":{"start":{"line":108,"column":1},"end":{"line":108,"column":1}},"children":[{"type":"text","value":"Despite not matching the eventually pattern, my mistakes seem to have cancelled each other out resulting in quite a nice looking torus. At some stage I will remake this using the latest version of the pattern for these parameters, for comparison.","position":{"start":{"line":108,"column":1},"end":{"line":108,"column":1}},"key":"iy7ILgYAIU"}],"key":"ThrCLphv5r"},{"type":"paragraph","position":{"start":{"line":110,"column":1},"end":{"line":110,"column":1}},"children":[{"type":"text","value":"The knot tied onto it is a ","position":{"start":{"line":110,"column":1},"end":{"line":110,"column":1}},"key":"UscOgEVA4M"},{"type":"link","url":"https://en.wikipedia.org/wiki/Cinquefoil_knot","position":{"start":{"line":110,"column":1},"end":{"line":110,"column":1}},"children":[{"type":"text","value":"cinquefoil","position":{"start":{"line":110,"column":1},"end":{"line":110,"column":1}},"key":"P51ZyIlq55"}],"urlSource":"https://en.wikipedia.org/wiki/Cinquefoil_knot","data":{"page":"Cinquefoil_knot","wiki":"https://en.wikipedia.org/","lang":"en"},"internal":false,"protocol":"wiki","key":"teKhhpt8L5"},{"type":"text","value":", or ","position":{"start":{"line":110,"column":1},"end":{"line":110,"column":1}},"key":"apFAxR83Ub"},{"type":"inlineMath","value":"(5,2)","position":{"start":{"line":110,"column":1},"end":{"line":110,"column":1}},"html":"<span class=\"katex\"><span class=\"katex-mathml\"><math xmlns=\"http://www.w3.org/1998/Math/MathML\"><semantics><mrow><mo stretchy=\"false\">(</mo><mn>5</mn><mo separator=\"true\">,</mo><mn>2</mn><mo stretchy=\"false\">)</mo></mrow><annotation encoding=\"application/x-tex\">(5,2)</annotation></semantics></math></span><span class=\"katex-html\" aria-hidden=\"true\"><span class=\"base\"><span class=\"strut\" style=\"height:1em;vertical-align:-0.25em;\"></span><span class=\"mopen\">(</span><span class=\"mord\">5</span><span class=\"mpunct\">,</span><span class=\"mspace\" style=\"margin-right:0.1667em;\"></span><span class=\"mord\">2</span><span class=\"mclose\">)</span></span></span></span>","key":"dHzl1GRqn2"},{"type":"text","value":" ","position":{"start":{"line":110,"column":1},"end":{"line":110,"column":1}},"key":"CtzeICojbu"},{"type":"link","url":"https://en.wikipedia.org/wiki/Torus_knot","position":{"start":{"line":110,"column":1},"end":{"line":110,"column":1}},"children":[{"type":"text","value":"torus knot","position":{"start":{"line":110,"column":1},"end":{"line":110,"column":1}},"key":"eEWC9DK62x"}],"urlSource":"https://en.wikipedia.org/wiki/Torus_knot","data":{"page":"Torus_knot","wiki":"https://en.wikipedia.org/","lang":"en"},"internal":false,"protocol":"wiki","key":"KjGPjoU8om"},{"type":"text","value":".","position":{"start":{"line":110,"column":1},"end":{"line":110,"column":1}},"key":"kTGAXSnYQw"}],"key":"r8pg75kh8n"}],"key":"cP5ulx1VYP"}],"key":"kDgveunuN1"},"references":{"cite":{"order":[],"data":{}}}}