{"version":3,"kind":"Notebook","sha256":"b0fef9b0063d3827a1b53d591878ef7bf2702946110e553efb1a26babe7152e4","slug":"index","location":"/intro.md","dependencies":[],"frontmatter":{"title":"Crochet maths","kernelspec":{"name":"python3","display_name":"Python 3"},"content_includes_title":false,"authors":[{"id":"Rosie Shewell Brockway","name":"Rosie Shewell Brockway"}],"numbering":{"code":{"enabled":false},"equation":{"enabled":false},"heading_1":{"enabled":true},"heading_2":{"enabled":true},"heading_3":{"enabled":true},"heading_4":{"enabled":true},"heading_5":{"enabled":true},"heading_6":{"enabled":true}},"thumbnail":"/crochet-increase-dec-cc50ef75f56f0a0f18dcfd75324d9aba.png","exports":[{"format":"md","filename":"intro.md","url":"/intro-4f4beda5c505c2ef4924ac5aa5fceb3f.md"}]},"mdast":{"type":"root","children":[{"type":"block","children":[{"type":"paragraph","position":{"start":{"line":9,"column":1},"end":{"line":9,"column":1}},"children":[{"type":"text","value":"A place for Rosie to write about maths and crochet.","position":{"start":{"line":9,"column":1},"end":{"line":9,"column":1}},"key":"UChefUwGAX"}],"key":"kxz4EyTk8a"},{"type":"block","children":[{"type":"heading","depth":2,"enumerated":false,"children":[{"type":"text","value":"Contents","position":{"start":{"line":11,"column":1},"end":{"line":11,"column":1}},"key":"XL0FPPe9JD"}],"identifier":"contents","label":"Contents","html_id":"contents","implicit":true,"key":"Ksi8ZHXUVD"},{"type":"list","children":[{"type":"listItem","children":[{"type":"link","url":"/","internal":true,"children":[{"type":"text","value":"Crochet maths","key":"dn3fXlNyiW"}],"urlSource":"/","key":"fZApQzQVGx"}],"key":"FAcVhGLZ9J"},{"type":"listItem","children":[{"type":"link","url":"/torus","internal":true,"children":[{"type":"text","value":"Torus","key":"ejyENGIeCj"}],"urlSource":"/torus","dataUrl":"/torus.json","protocol":"file","key":"VuFbLNJugi"}],"key":"NeegbFaLcm"},{"type":"listItem","children":[{"type":"link","url":"/interactive-torus-crochet","internal":true,"children":[{"type":"text","value":"Interactive torus crochet pattern","key":"sgimNPzqFj"}],"urlSource":"/interactive-torus-crochet","dataUrl":"/interactive-torus-crochet.json","protocol":"file","key":"O7eFCdI3oK"}],"key":"KC8zfedwhD"},{"type":"listItem","children":[{"type":"link","url":"/interactive-toral-geodesics","internal":true,"children":[{"type":"text","value":"Interactive toral geodesics","key":"v6pl5kdOQr"}],"urlSource":"/interactive-toral-geodesics","dataUrl":"/interactive-toral-geodesics.json","protocol":"file","key":"m4kwVPA5ZW"}],"key":"ecAOyJ9TJN"},{"type":"listItem","children":[{"type":"link","url":"/gallery","internal":true,"children":[{"type":"text","value":"Gallery","key":"YAMamFpc6m"}],"urlSource":"/gallery","dataUrl":"/gallery.json","protocol":"file","key":"uPivWnVuRw"}],"key":"bjpkTCIkxk"},{"type":"listItem","children":[{"type":"link","url":"/tonnetz","internal":true,"children":[{"type":"text","value":"Crochet tonnetz","key":"JkmuG5tvXL"}],"urlSource":"/tonnetz","dataUrl":"/tonnetz.json","protocol":"file","key":"eDjB1Ix7ef"}],"key":"v4ptDhkLT6"}],"key":"U9sAdskJbj"}],"data":{"part":"toc:project"},"key":"Idw3jHoC7h"},{"type":"container","kind":"figure","children":[{"type":"image","url":"/crochet-increase-dec-cc50ef75f56f0a0f18dcfd75324d9aba.png","alt":"Crochet increases and decreases.","width":"400","data":{"altTextIsAutoGenerated":true},"key":"JgQzDz0OGB","urlSource":"figs/crochet-increase-decrease.png"},{"type":"caption","children":[{"type":"paragraph","position":{"start":{"line":20,"column":1},"end":{"line":20,"column":1}},"children":[{"type":"captionNumber","kind":"figure","label":"fig:crochet-inc","identifier":"fig:crochet-inc","html_id":"fig-crochet-inc","enumerator":"1","children":[{"type":"text","value":"Figure ","key":"SXNMsAkRHi"},{"type":"text","value":"1","key":"v3bnb8c5ZW"},{"type":"text","value":":","key":"PXy9XxYDrM"}],"template":"Figure %s:","key":"U5638aR9dc"},{"type":"text","value":"Crochet increases and decreases.","position":{"start":{"line":20,"column":1},"end":{"line":20,"column":1}},"key":"LrsrmtJEcd"}],"key":"uqyK25FUQA"}],"key":"xU99Qyohqp"}],"label":"fig:crochet-inc","identifier":"fig:crochet-inc","enumerator":"1","html_id":"fig-crochet-inc","key":"jTIaZ9z6oK"}],"key":"BXO0HGC1Xj"}],"key":"zZq7eDbeOb"},"references":{"cite":{"order":[],"data":{}}}}